{
  "name": "plugin-vscodelite-edit",
  "author": "Emptylight",
  "url": "https://github.com/emptylight370/plugin-vscodelite-edit",
  "version": "0.0.1",
  "minAppVersion": "3.3.0",
  "backends": [
    "windows",
    "linux",
    "darwin",
    "ios",
    "android",
    "harmony",
    "docker"
  ],
  "frontends": [
    "desktop",
    "mobile",
    "browser-desktop",
    "browser-mobile",
    "desktop-window"
  ],
  "disabledInPublish": true,
  "displayName": {
    "default": "VSCode Lite Edit"
  },
  "description": {
    "default": "This is a plugin build for theme VSCode Lite Edit",
    "zh_CN": "这是一个为主题VSCode Lite Edit构建的插件"
  },
  "readme": {
    "default": "README.md",
    "zh_CN": "README_zh_CN.md"
  },
  "funding": {
    "openCollective": "",
    "patreon": "",
    "github": "",
    "custom": [
      "https://afdian.com/a/tingyuting"
    ]
  },
  "keywords": [
    "vscode",
    "vscodelite",
    "vscode lite",
    "VSCE",
    "VSCE主题",
    "light",
    "dark",
    "emptylight",
    "emptylight370"
  ]
}
